{
  "titulo": {
    "es": "¿Qué dice la Biblia sobre el autocontrol?",
    "en": "What does the Bible say about self-control?"
  },
  "contenido": {
    "es": "Es parte del fruto del espíritu y nos ayuda a tomar decisiones sabias.",
    "en": "It is part of the fruit of the spirit and helps us make wise decisions."
  },
  "respuesta": {
    "es": "",
    "en": ""
  },
  "cita": "",
  "link": "",
  "argumentos": {
    "argumentos_biblicos": [],
    "argumentos_logicos": [],
    "argumentos_historicos": [],
    "fuentes_recomendadas": []
  },
  "secciones": [],
  "versiculos": [
    "Gálatas 5:22-23"
  ],
  "enlaces": [],
  "conclusion": {
    "es": "",
    "en": ""
  },
  "copyright": {
    "es": "© 2025 Watch Tower Bible and Tract Society of Pennsylvania. Usado con fines educativos sin ánimo de lucro.",
    "en": "© 2025 Watch Tower Bible and Tract Society of Pennsylvania. Used for educational, non-commercial purposes."
  }
}