{
  "titulo": {
    "es": "¿Qué dice la Biblia sobre la avaricia?",
    "en": "What does the Bible say about greed?"
  },
  "contenido": {
    "es": "La avaricia puede alejarnos de Dios.",
    "en": "Greed can distance us from God."
  },
  "respuesta": {
    "es": "",
    "en": ""
  },
  "cita": "",
  "link": "",
  "argumentos": {
    "argumentos_biblicos": [],
    "argumentos_logicos": [],
    "argumentos_historicos": [],
    "fuentes_recomendadas": []
  },
  "secciones": [],
  "versiculos": [
    "1 Timoteo 6:9-10"
  ],
  "enlaces": [],
  "conclusion": {
    "es": "",
    "en": ""
  },
  "copyright": {
    "es": "© 2025 Watch Tower Bible and Tract Society of Pennsylvania. Usado con fines educativos sin ánimo de lucro.",
    "en": "© 2025 Watch Tower Bible and Tract Society of Pennsylvania. Used for educational, non-commercial purposes."
  }
}